nprobust/__init__.py
nprobust/kdbwselect.py
nprobust/kdrobust.py
nprobust/lpbwselect.py
nprobust/lprobust.py
nprobust/npfunctions.py
nprobust/nprobust_plot.py
nprobust-0.5.0.dist-info/METADATA
nprobust-0.5.0.dist-info/WHEEL
nprobust-0.5.0.dist-info/top_level.txt
nprobust-0.5.0.dist-info/RECORD
