Metadata-Version: 2.4
Name: nprobust
Version: 0.5.0
Summary: Nonparametric Robust Estimation and Inference Methods
Home-page: https://github.com/nppackages/nprobust
Author: Calonico, Cattaneo, and Farrell
License: GPL-2.0
Project-URL: Homepage, https://github.com/nppackages/nprobust
Project-URL: Repository, https://github.com/nppackages/nprobust
Project-URL: Documentation, https://nppackages.github.io/nprobust/
Keywords: nonparametric,regression,kernel density,bandwidth selection,robust inference,local polynomial
Classifier: Development Status :: 4 - Beta
Classifier: Intended Audience :: Science/Research
Classifier: License :: OSI Approved :: GNU General Public License v2 (GPLv2)
Classifier: Operating System :: OS Independent
Classifier: Programming Language :: Python :: 3
Classifier: Programming Language :: Python :: 3.8
Classifier: Programming Language :: Python :: 3.9
Classifier: Programming Language :: Python :: 3.10
Classifier: Programming Language :: Python :: 3.11
Classifier: Programming Language :: Python :: 3.12
Classifier: Topic :: Scientific/Engineering :: Mathematics
Classifier: Topic :: Scientific/Engineering :: Information Analysis
Requires-Python: >=3.8
Requires-Dist: numpy>=1.20.0
Requires-Dist: scipy>=1.7.0
Provides-Extra: plotting
Requires-Dist: matplotlib>=3.4.0; extra == "plotting"
Provides-Extra: dev
Requires-Dist: pytest>=6.0; extra == "dev"
Requires-Dist: matplotlib>=3.4.0; extra == "dev"
Requires-Dist: build; extra == "dev"
Requires-Dist: twine; extra == "dev"
Dynamic: home-page
Dynamic: requires-python
